{
  "serverMaxRevisionCounter": 41,
  "sourceMembers": {
    "Profile__Admin": {
      "serverRevisionCounter": 40,
      "lastRetrievedFromServer": 40,
      "memberType": "Profile",
      "isNameObsolete": false
    },
    "RecordType__Contact.contact_id": {
      "serverRevisionCounter": 38,
      "lastRetrievedFromServer": 38,
      "memberType": "RecordType",
      "isNameObsolete": false
    },
    "ApexClass__DefaultPreferenceCenterApexClass": {
      "serverRevisionCounter": 37,
      "lastRetrievedFromServer": 37,
      "memberType": "ApexClass",
      "isNameObsolete": false
    },
    "CustomApplication__privacycenter__PrivacyCenter": {
      "serverRevisionCounter": 39,
      "lastRetrievedFromServer": 39,
      "memberType": "CustomApplication",
      "isNameObsolete": false
    },
    "PermissionSet__Perm_Set_forDefault_Preference_Manager_Configuration": {
      "serverRevisionCounter": 41,
      "lastRetrievedFromServer": 41,
      "memberType": "PermissionSet",
      "isNameObsolete": false
    },
    "CustomMetadata__privacycenter__Data_Field.f0a10c0b26929338f9042ea7c4cd10": {
      "serverRevisionCounter": 2,
      "lastRetrievedFromServer": 2,
      "memberType": "CustomMetadata",
      "isNameObsolete": false
    },
    "CustomMetadata__privacycenter__Data_Field.f127f1e618edb6274879bdc58d112e": {
      "serverRevisionCounter": 3,
      "lastRetrievedFromServer": 3,
      "memberType": "CustomMetadata",
      "isNameObsolete": false
    },
    "CustomMetadata__privacycenter__Data_Field.f156d6e450378fd2ea80a6c0487f26": {
      "serverRevisionCounter": 4,
      "lastRetrievedFromServer": 4,
      "memberType": "CustomMetadata",
      "isNameObsolete": false
    },
    "CustomMetadata__privacycenter__Data_Field.f1fa4bb92b911752e45182af503673": {
      "serverRevisionCounter": 5,
      "lastRetrievedFromServer": 5,
      "memberType": "CustomMetadata",
      "isNameObsolete": false
    },
    "CustomMetadata__privacycenter__Data_Field.f2afd89ef52b739fb2a60e62dd9f42": {
      "serverRevisionCounter": 6,
      "lastRetrievedFromServer": 6,
      "memberType": "CustomMetadata",
      "isNameObsolete": false
    },
    "CustomMetadata__privacycenter__Data_Field.f56ac3d22780a305d43a76c6354c3c": {
      "serverRevisionCounter": 7,
      "lastRetrievedFromServer": 7,
      "memberType": "CustomMetadata",
      "isNameObsolete": false
    },
    "CustomMetadata__privacycenter__Data_Field.f6d7e708e940c3b8faca776e7a1035": {
      "serverRevisionCounter": 8,
      "lastRetrievedFromServer": 8,
      "memberType": "CustomMetadata",
      "isNameObsolete": false
    },
    "CustomMetadata__privacycenter__Data_Field.f6e11f51570ae0b90c79278d29fc35": {
      "serverRevisionCounter": 9,
      "lastRetrievedFromServer": 9,
      "memberType": "CustomMetadata",
      "isNameObsolete": false
    },
    "CustomMetadata__privacycenter__Data_Field.f78ae140445d015c6a8efaf4a6cfac": {
      "serverRevisionCounter": 10,
      "lastRetrievedFromServer": 10,
      "memberType": "CustomMetadata",
      "isNameObsolete": false
    },
    "CustomMetadata__privacycenter__Data_Field.f79af374e1034c435bad34ebcf7282": {
      "serverRevisionCounter": 11,
      "lastRetrievedFromServer": 11,
      "memberType": "CustomMetadata",
      "isNameObsolete": false
    },
    "CustomMetadata__privacycenter__Data_Field.f7bffdbae61848c2f35313103eb3af": {
      "serverRevisionCounter": 12,
      "lastRetrievedFromServer": 12,
      "memberType": "CustomMetadata",
      "isNameObsolete": false
    },
    "CustomMetadata__privacycenter__Data_Field.f87449342b4f9586282acd464e9e64": {
      "serverRevisionCounter": 13,
      "lastRetrievedFromServer": 13,
      "memberType": "CustomMetadata",
      "isNameObsolete": false
    },
    "CustomMetadata__privacycenter__Data_Field.f8d9b96e5b3e29bc03034cc0b41eac": {
      "serverRevisionCounter": 14,
      "lastRetrievedFromServer": 14,
      "memberType": "CustomMetadata",
      "isNameObsolete": false
    },
    "CustomMetadata__privacycenter__Data_Field.f9c86b2d93a99ed162425c7415c69f": {
      "serverRevisionCounter": 15,
      "lastRetrievedFromServer": 15,
      "memberType": "CustomMetadata",
      "isNameObsolete": false
    },
    "CustomMetadata__privacycenter__Data_Field.fa82320cfd98c81c55c677d673003e": {
      "serverRevisionCounter": 16,
      "lastRetrievedFromServer": 16,
      "memberType": "CustomMetadata",
      "isNameObsolete": false
    },
    "CustomMetadata__privacycenter__Data_Field.fab2fae3e02a65a1c0db279e89cd27": {
      "serverRevisionCounter": 17,
      "lastRetrievedFromServer": 17,
      "memberType": "CustomMetadata",
      "isNameObsolete": false
    },
    "CustomMetadata__privacycenter__Data_Field.fadd7dcf69cdea596a18e9e3ec7c76": {
      "serverRevisionCounter": 18,
      "lastRetrievedFromServer": 18,
      "memberType": "CustomMetadata",
      "isNameObsolete": false
    },
    "CustomMetadata__privacycenter__Data_Field.fb5fffb1987629b8b68610be567399": {
      "serverRevisionCounter": 19,
      "lastRetrievedFromServer": 19,
      "memberType": "CustomMetadata",
      "isNameObsolete": false
    },
    "CustomMetadata__privacycenter__Data_Field.fb660d2ea092e2c9a8f43995b4211d": {
      "serverRevisionCounter": 20,
      "lastRetrievedFromServer": 20,
      "memberType": "CustomMetadata",
      "isNameObsolete": false
    },
    "CustomMetadata__privacycenter__Data_Field.fcef11944b7e434bc03ba03db1144a": {
      "serverRevisionCounter": 21,
      "lastRetrievedFromServer": 21,
      "memberType": "CustomMetadata",
      "isNameObsolete": false
    },
    "CustomMetadata__privacycenter__Data_Field.fd053ecdc2a93b0aa8aca6c50034f8": {
      "serverRevisionCounter": 22,
      "lastRetrievedFromServer": 22,
      "memberType": "CustomMetadata",
      "isNameObsolete": false
    },
    "CustomMetadata__privacycenter__Data_Field.fd7f0d09a5fbe99990c6ede69172f9": {
      "serverRevisionCounter": 23,
      "lastRetrievedFromServer": 23,
      "memberType": "CustomMetadata",
      "isNameObsolete": false
    },
    "CustomMetadata__privacycenter__Data_Field.fdb8188ff6490bee495dd757fbeba0": {
      "serverRevisionCounter": 24,
      "lastRetrievedFromServer": 24,
      "memberType": "CustomMetadata",
      "isNameObsolete": false
    },
    "CustomMetadata__privacycenter__Data_Field.fe626397e5c69c0b938f44c1d92312": {
      "serverRevisionCounter": 25,
      "lastRetrievedFromServer": 25,
      "memberType": "CustomMetadata",
      "isNameObsolete": false
    },
    "CustomMetadata__privacycenter__Data_Field.fed09cb8247ec1355c745d565067cd": {
      "serverRevisionCounter": 26,
      "lastRetrievedFromServer": 26,
      "memberType": "CustomMetadata",
      "isNameObsolete": false
    },
    "CustomMetadata__privacycenter__Data_Field.fee7e87ac748c79fa9befb31c2712e": {
      "serverRevisionCounter": 27,
      "lastRetrievedFromServer": 27,
      "memberType": "CustomMetadata",
      "isNameObsolete": false
    },
    "CustomMetadata__privacycenter__Data_Field.ff61a6f1387c8afb968ed719224cbf": {
      "serverRevisionCounter": 28,
      "lastRetrievedFromServer": 28,
      "memberType": "CustomMetadata",
      "isNameObsolete": false
    },
    "CustomMetadata__privacycenter__Data_Field.ffd60b93833fa495de3fa0ebcb0c31": {
      "serverRevisionCounter": 29,
      "lastRetrievedFromServer": 29,
      "memberType": "CustomMetadata",
      "isNameObsolete": false
    },
    "CustomMetadata__privacycenter__Data_Object.o09937f20c575048c11085b891997b": {
      "serverRevisionCounter": 30,
      "lastRetrievedFromServer": 30,
      "memberType": "CustomMetadata",
      "isNameObsolete": false
    },
    "CustomMetadata__privacycenter__Data_Object.o27f9d15c3bba15be06f2990346384": {
      "serverRevisionCounter": 31,
      "lastRetrievedFromServer": 31,
      "memberType": "CustomMetadata",
      "isNameObsolete": false
    },
    "CustomMetadata__privacycenter__Data_Object.o986f539d53dd0062d032a059fc042": {
      "serverRevisionCounter": 32,
      "lastRetrievedFromServer": 32,
      "memberType": "CustomMetadata",
      "isNameObsolete": false
    },
    "CustomMetadata__privacycenter__Data_Policy.ArchiveCases": {
      "serverRevisionCounter": 33,
      "lastRetrievedFromServer": 33,
      "memberType": "CustomMetadata",
      "isNameObsolete": false
    },
    "CustomMetadata__privacycenter__Data_Policy.CaseArchive": {
      "serverRevisionCounter": 34,
      "lastRetrievedFromServer": 34,
      "memberType": "CustomMetadata",
      "isNameObsolete": false
    },
    "CustomMetadata__privacycenter__Data_Policy.DeleteContact": {
      "serverRevisionCounter": 35,
      "lastRetrievedFromServer": 35,
      "memberType": "CustomMetadata",
      "isNameObsolete": false
    },
    "CustomMetadata__privacycenter__Data_Policy.RetainCase": {
      "serverRevisionCounter": 36,
      "lastRetrievedFromServer": 36,
      "memberType": "CustomMetadata",
      "isNameObsolete": false
    }
  }
}